veriq/__init__.py
veriq/__main__.py
veriq/_bounded_models.py
veriq/_cli/__init__.py
veriq/_cli/config.py
veriq/_cli/discover.py
veriq/_cli/graph_query.py
veriq/_cli/graph_render.py
veriq/_cli/main.py
veriq/_cli/render_trace.py
veriq/_cli/tui/__init__.py
veriq/_cli/tui/app.py
veriq/_cli/tui/data.py
veriq/_cli/tui/screens.py
veriq/_cli/tui/widgets.py
veriq/_context.py
veriq/_decorators.py
veriq/_default.py
veriq/_eval.py
veriq/_eval_engine/__init__.py
veriq/_eval_engine/_engine.py
veriq/_eval_engine/_resolution.py
veriq/_external_data.py
veriq/_graph/__init__.py
veriq/_graph/_algorithms.py
veriq/_graph/_dependency_graph.py
veriq/_io.py
veriq/_ir/__init__.py
veriq/_ir/_builder.py
veriq/_ir/_graph_spec.py
veriq/_ir/_node_spec.py
veriq/_models.py
veriq/_path.py
veriq/_relations.py
veriq/_table.py
veriq/_toml_edit.py
veriq/_traceability.py
veriq/_update.py
veriq/py.typed
veriq-0.3.1.dist-info/licenses/LICENSE
veriq-0.3.1.dist-info/WHEEL
veriq-0.3.1.dist-info/entry_points.txt
veriq-0.3.1.dist-info/METADATA
veriq-0.3.1.dist-info/RECORD
