Metadata-Version: 2.4
Name: veriq
Version: 0.3.1
Summary: A lightweight Python library for managing system requirements, verifications, and design.
Author: Shunichiro Nomura
Author-email: Shunichiro Nomura <nomura@space.t.u-tokyo.ac.jp>
License-Expression: MIT
License-File: LICENSE
Classifier: Development Status :: 3 - Alpha
Classifier: License :: OSI Approved :: MIT License
Classifier: Programming Language :: Python
Classifier: Programming Language :: Python :: 3 :: Only
Classifier: Programming Language :: Python :: 3.14
Classifier: Typing :: Typed
Requires-Dist: bounded-models>=0.0.3
Requires-Dist: pydantic>=2.11.7
Requires-Dist: rich>=14.0.0
Requires-Dist: scoped-context>=0.0.1
Requires-Dist: textual>=7.3.0
Requires-Dist: tomli-w>=1.1.0
Requires-Dist: tomlkit>=0.14.0
Requires-Dist: typer>=0.16.1
Requires-Python: >=3.14
Project-URL: Issues, https://github.com/shunichironomura/veriq/issues
Project-URL: Repository, https://github.com/shunichironomura/veriq
